{"frames": {

"big_win_ro-RON":
{
	"frame": {"x":1,"y":1,"w":223,"h":76},
	"rotated": false,
	"trimmed": false,
	"spriteSourceSize": {"x":0,"y":0,"w":223,"h":76},
	"sourceSize": {"w":223,"h":76}
}},
"meta": {
	"app": "https://www.codeandweb.com/texturepacker",
	"version": "1.0",
	"image": "Local-ron-0@0.375.png",
	"format": "RGBA8888",
	"size": {"w":225,"h":78},
	"scale": "0.25",
	"smartupdate": "$TexturePacker:SmartUpdate:a65867356d2322316550f5417dcf7b6d:8eab5988634e120ebcdd408f36dca579:22cc6a871243d6fd4053f934beb32746$"
}
}
